src2md/__init__.py
src2md/__main__.py
src2md/cli.py
src2md/core/__init__.py
src2md/core/context.py
src2md/core/repository.py
src2md/formatters/__init__.py
src2md/formatters/base.py
src2md/formatters/html.py
src2md/formatters/json.py
src2md/formatters/markdown.py
src2md/strategies/__init__.py
src2md/strategies/importance.py
src2md/strategies/llm_summarizer.py
src2md/strategies/summarization.py
src2md/tests/unit/test_smart_truncation.py
src2md/tests/unit/test_summarization.py
src2md-2.1.0.dist-info/licenses/LICENSE
src2md-2.1.0.dist-info/METADATA
src2md-2.1.0.dist-info/WHEEL
src2md-2.1.0.dist-info/entry_points.txt
src2md-2.1.0.dist-info/top_level.txt
src2md-2.1.0.dist-info/RECORD
