Metadata-Version: 2.4
Name: src2md
Version: 2.1.0
Summary: Convert source code to structured, context-optimized markdown for LLMs with intelligent summarization
Home-page: https://github.com/queelius/src2md
Author: Alex Towell
Author-email: Alex Towell <lex@metafunctor.com>
License: MIT License
Project-URL: Homepage, https://github.com/queelius/src2md
Project-URL: Bug Tracker, https://github.com/queelius/src2md/issues
Project-URL: Documentation, https://github.com/queelius/src2md/blob/main/README.md
Project-URL: Changelog, https://github.com/queelius/src2md/blob/main/CHANGELOG.md
Keywords: markdown,source code,documentation,llm,context-window,code-analysis,summarization,ast,code-compression
Classifier: Development Status :: 5 - Production/Stable
Classifier: Intended Audience :: Developers
Classifier: License :: OSI Approved :: MIT License
Classifier: Operating System :: OS Independent
Classifier: Programming Language :: Python :: 3
Classifier: Programming Language :: Python :: 3.8
Classifier: Programming Language :: Python :: 3.9
Classifier: Programming Language :: Python :: 3.10
Classifier: Programming Language :: Python :: 3.11
Classifier: Programming Language :: Python :: 3.12
Classifier: Topic :: Software Development :: Documentation
Classifier: Topic :: Text Processing :: Markup :: Markdown
Classifier: Topic :: Software Development :: Libraries :: Python Modules
Requires-Python: >=3.8
License-File: LICENSE
Requires-Dist: rich>=13.0.0
Requires-Dist: tiktoken>=0.5.0
Requires-Dist: pyyaml>=6.0
Requires-Dist: pathspec>=0.11.0
Requires-Dist: astroid>=3.0.0
Provides-Extra: llm
Requires-Dist: openai>=1.0.0; extra == "llm"
Requires-Dist: anthropic>=0.8.0; extra == "llm"
Provides-Extra: dev
Requires-Dist: pytest>=7.4.0; extra == "dev"
Requires-Dist: pytest-cov>=4.1.0; extra == "dev"
Requires-Dist: pytest-mock>=3.11.0; extra == "dev"
Requires-Dist: pytest-timeout>=2.1.0; extra == "dev"
Requires-Dist: black>=23.0.0; extra == "dev"
Requires-Dist: ruff>=0.1.0; extra == "dev"
Requires-Dist: mypy>=1.0.0; extra == "dev"
Dynamic: author
Dynamic: home-page
Dynamic: license-file
Dynamic: requires-python
